yosafe_packages/yosafe_subpackage_2/__init__.py
yosafe_packages/yosafe_subpackage_2/yosafe_subpackage_2_functions.py
yosafe_subpackage_2-0.1.2.dist-info/METADATA
yosafe_subpackage_2-0.1.2.dist-info/WHEEL
yosafe_subpackage_2-0.1.2.dist-info/RECORD
