Metadata-Version: 2.1
Name: yosafe_subpackage_2
Version: 0.1.2
Summary: 
Author: Yo581515
Author-email: 581515@stud.hvl.no
Requires-Python: >=3.9,<4.0.0
Classifier: Programming Language :: Python :: 3
Classifier: Programming Language :: Python :: 3.9
Classifier: Programming Language :: Python :: 3.10
Classifier: Programming Language :: Python :: 3.11
Classifier: Programming Language :: Python :: 3.12
Requires-Dist: pydantic (>=2.9.1,<3.0.0)
Requires-Dist: pytest (>=8.3.2,<9.0.0)
Requires-Dist: requests (>=2.32.3,<3.0.0)
Requires-Dist: yosafe-subpackage-1 (>=0.1.2,<0.2.0)
